discord_booster/__init__.py
discord_booster/booster.py
discord_booster-0.9.dist-info/METADATA
discord_booster-0.9.dist-info/WHEEL
discord_booster-0.9.dist-info/entry_points.txt
discord_booster-0.9.dist-info/top_level.txt
discord_booster-0.9.dist-info/RECORD
