Metadata-Version: 2.4
Name: discord-booster
Version: 0.9
Requires-Dist: requests
Requires-Dist: colorama
Dynamic: requires-dist
